README.md
setup.py
tartisan/VERSION.py
tartisan/__init__.py
tartisan.egg-info/PKG-INFO
tartisan.egg-info/SOURCES.txt
tartisan.egg-info/dependency_links.txt
tartisan.egg-info/not-zip-safe
tartisan.egg-info/requires.txt
tartisan.egg-info/top_level.txt
test/test.py