Metadata-Version: 2.1
Name: tartisan
Version: 0.1.0.dev3
Summary: tartisan
Home-page: https://github.com/yuezhihan/geyser
Author: Zhihan Yue
Author-email: zhihan.yue@foxmail.com
License: UNKNOWN
Platform: UNKNOWN
Classifier: License :: OSI Approved :: MIT License
Requires-Python: >=2.7
